{"nodes": [{"id": "template_dash", "label": "WebUI/templates/dash.html (Full dashboard)", "file_type": "code", "source_file": "System/WebUI/templates/dash.html", "source_location": null, "source_url": null, "captured_at": null, "author": null, "contributor": null}, {"id": "api_ui_status", "label": "GET /api/ui/status", "file_type": "code", "source_file": "System/WebUI/templates/dash.html", "source_location": "line 63", "source_url": null, "captured_at": null, "author": null, "contributor": null}, {"id": "api_ui_camera_preset", "label": "POST /api/ui/camera/preset", "file_type": "code", "source_file": "System/WebUI/templates/dash.html", "source_location": "line 66", "source_url": null, "captured_at": null, "author": null, "contributor": null}, {"id": "api_ui_camera", "label": "POST /api/ui/camera", "file_type": "code", "source_file": "System/WebUI/templates/dash.html", "source_location": "line 67", "source_url": null, "captured_at": null, "author": null, "contributor": null}, {"id": "api_ui_audio", "label": "POST /api/ui/audio", "file_type": "code", "source_file": "System/WebUI/templates/dash.html", "source_location": "line 68", "source_url": null, "captured_at": null, "author": null, "contributor": null}, {"id": "api_config_patch", "label": "PATCH /api/config (hot-reload config)", "file_type": "code", "source_file": "System/WebUI/templates/dash.html", "source_location": "line 69", "source_url": null, "captured_at": null, "author": null, "contributor": null}, {"id": "adam_config_inject", "label": "__ADAM_CONFIG__ (server-injected config object)", "file_type": "rationale", "source_file": "System/WebUI/templates/dash.html", "source_location": "line 36", "source_url": null, "captured_at": null, "author": null, "contributor": null}, {"id": "api_ui_video_latency_reset", "label": "POST /api/ui/video-latency/reset", "file_type": "code", "source_file": "System/WebUI/templates/dash.html", "source_location": "line 71", "source_url": null, "captured_at": null, "author": null, "contributor": null}], "edges": [{"source": "template_dash", "target": "api_ui_status", "relation": "calls", "confidence": "EXTRACTED", "confidence_score": 1.0, "source_file": "System/WebUI/templates/dash.html", "source_location": "line 63", "weight": 1.0}, {"source": "template_dash", "target": "api_ui_camera_preset", "relation": "calls", "confidence": "EXTRACTED", "confidence_score": 1.0, "source_file": "System/WebUI/templates/dash.html", "source_location": "line 66", "weight": 1.0}, {"source": "template_dash", "target": "api_ui_camera", "relation": "calls", "confidence": "EXTRACTED", "confidence_score": 1.0, "source_file": "System/WebUI/templates/dash.html", "source_location": "line 67", "weight": 1.0}, {"source": "template_dash", "target": "api_ui_audio", "relation": "calls", "confidence": "EXTRACTED", "confidence_score": 1.0, "source_file": "System/WebUI/templates/dash.html", "source_location": "line 68", "weight": 1.0}, {"source": "template_dash", "target": "api_config_patch", "relation": "calls", "confidence": "EXTRACTED", "confidence_score": 1.0, "source_file": "System/WebUI/templates/dash.html", "source_location": "line 69", "weight": 1.0}, {"source": "template_dash", "target": "api_ui_video_latency_reset", "relation": "calls", "confidence": "EXTRACTED", "confidence_score": 1.0, "source_file": "System/WebUI/templates/dash.html", "source_location": "line 71", "weight": 1.0}, {"source": "template_dash", "target": "adam_config_inject", "relation": "references", "confidence": "EXTRACTED", "confidence_score": 1.0, "source_file": "System/WebUI/templates/dash.html", "source_location": "line 36", "weight": 1.0}, {"source": "api_config_patch", "target": "adam_tuning_module", "relation": "conceptually_related_to", "confidence": "INFERRED", "confidence_score": 0.85, "source_file": "System/WebUI/templates/dash.html", "source_location": "line 69", "weight": 0.85}, {"source": "orchestrator_py", "target": "api_ui_status", "relation": "implements", "confidence": "INFERRED", "confidence_score": 0.85, "source_file": "System/WebUI/templates/dash.html", "source_location": "line 63", "weight": 0.85}, {"source": "orchestrator_py", "target": "api_config_patch", "relation": "implements", "confidence": "INFERRED", "confidence_score": 0.85, "source_file": "System/WebUI/templates/dash.html", "source_location": "line 69", "weight": 0.85}, {"source": "adam_config_inject", "target": "adam_settings_load", "relation": "semantically_similar_to", "confidence": "INFERRED", "confidence_score": 0.75, "source_file": "System/WebUI/templates/dash.html", "source_location": "line 36", "weight": 0.75}, {"source": "template_dash", "target": "template_debug", "relation": "references", "confidence": "EXTRACTED", "confidence_score": 1.0, "source_file": "System/WebUI/templates/dash.html", "source_location": "line 18", "weight": 1.0}, {"source": "template_dash", "target": "template_agent", "relation": "references", "confidence": "EXTRACTED", "confidence_score": 1.0, "source_file": "System/WebUI/templates/dash.html", "source_location": "line 18", "weight": 1.0}, {"source": "template_dash", "target": "esp32_mcu", "relation": "references", "confidence": "INFERRED", "confidence_score": 0.85, "source_file": "System/WebUI/templates/dash.html", "source_location": "line 53", "weight": 0.85}], "hyperedges": []}